multi_rate_limit/__init__.py
multi_rate_limit/multi_rate_limit.py
multi_rate_limit/rate_limit.py
multi_rate_limit/resource_queue.py
multi_rate_limit-0.2.0.dist-info/LICENSE
multi_rate_limit-0.2.0.dist-info/METADATA
multi_rate_limit-0.2.0.dist-info/WHEEL
multi_rate_limit-0.2.0.dist-info/RECORD
