Metadata-Version: 2.1
Name: multi-rate-limit
Version: 0.2.0
Summary: Package for using multiple resources while observing multiple RateLimits.
Author: largetownsky
Author-email: large.town.sky@gmail.com
Requires-Python: >=3.10,<4.0
Classifier: Programming Language :: Python :: 3
Classifier: Programming Language :: Python :: 3.10
Classifier: Programming Language :: Python :: 3.11
Classifier: Programming Language :: Python :: 3.12
Requires-Dist: aiofiles (>=23.2.1,<24.0.0)
Project-URL: documentation, https://largetownsky.github.io/multi-rate-limit/
Project-URL: repository, https://github.com/largetownsky/multi-rate-limit
